epss_checker/__init__.py
epss_checker/epss_checker.py
epss_checker-1.0.dist-info/LICENSE
epss_checker-1.0.dist-info/METADATA
epss_checker-1.0.dist-info/WHEEL
epss_checker-1.0.dist-info/entry_points.txt
epss_checker-1.0.dist-info/top_level.txt
epss_checker-1.0.dist-info/RECORD
