Metadata-Version: 2.1
Name: epss-checker
Version: 1.0
Summary: A client to query the FIRST EPSS API for CVE EPSS scores
Home-page: https://github.com/santosomar/epss-client
Author: Omar Santos
Author-email: santosomar@gmail.com
Classifier: Programming Language :: Python :: 3
Classifier: License :: OSI Approved :: MIT License
Classifier: Operating System :: OS Independent
License-File: LICENSE
Requires-Dist: requests
